mealdb/__init__.py
py_mealdb-0.1.7.dist-info/LICENSE
py_mealdb-0.1.7.dist-info/METADATA
py_mealdb-0.1.7.dist-info/WHEEL
py_mealdb-0.1.7.dist-info/RECORD
