Metadata-Version: 2.1
Name: py-mealdb
Version: 0.1.7
Summary: The MealDB API wrapper
License: CC-BY-NC-SA-4.0
Keywords: api,cooking
Author: Sherwin-14
Author-email: varghesesheriwn@gmail.com
Requires-Python: >=3.11,<4.0
Classifier: License :: Other/Proprietary License
Classifier: Programming Language :: Python :: 3
Classifier: Programming Language :: Python :: 3.11
Classifier: Programming Language :: Python :: 3.12
Requires-Dist: httpx (>=0.28.1,<0.29.0)
